[{"id":1,"first_name":"Ernestus","last_name":"Sheehan","email":"esheehan0@salon.com","saldo":7002932,"avatar":"https://robohash.org/sitoditsit.png?size=50x50&set=set1"},
{"id":2,"first_name":"Waverly","last_name":"Lugton","email":"wlugton1@umich.edu","saldo":4570201,"avatar":"https://robohash.org/autmaximeipsam.png?size=50x50&set=set1"},
{"id":3,"first_name":"Ashlan","last_name":"Simenet","email":"asimenet2@npr.org","saldo":998928,"avatar":"https://robohash.org/sintvoluptateid.png?size=50x50&set=set1"},
{"id":4,"first_name":"Linea","last_name":"Petrillo","email":"lpetrillo3@wordpress.com","saldo":8000079,"avatar":"https://robohash.org/consequaturperspiciatissequi.png?size=50x50&set=set1"},
{"id":5,"first_name":"Jerrie","last_name":"Furman","email":"jfurman4@jiathis.com","saldo":7383100,"avatar":"https://robohash.org/omnisoptioexpedita.png?size=50x50&set=set1"},
{"id":6,"first_name":"Nettie","last_name":"Cockrell","email":"ncockrell5@google.es","saldo":835798,"avatar":"https://robohash.org/velfugaautem.png?size=50x50&set=set1"},
{"id":7,"first_name":"Yance","last_name":"Gomer","email":"ygomer6@icio.us","saldo":2388867,"avatar":"https://robohash.org/teneturreprehenderitautem.png?size=50x50&set=set1"},
{"id":8,"first_name":"Vernor","last_name":"Mintram","email":"vmintram7@oracle.com","saldo":6074540,"avatar":"https://robohash.org/asperioresnisilaudantium.png?size=50x50&set=set1"},
{"id":9,"first_name":"Quintana","last_name":"Orgen","email":"qorgen8@ucoz.ru","saldo":3434320,"avatar":"https://robohash.org/avoluptasut.png?size=50x50&set=set1"},
{"id":10,"first_name":"Aloysius","last_name":"Wigginton","email":"awigginton9@sitemeter.com","saldo":4418461,"avatar":"https://robohash.org/nequenihilet.png?size=50x50&set=set1"},
{"id":11,"first_name":"Travis","last_name":"Coverley","email":"tcoverleya@vk.com","saldo":9067467,"avatar":"https://robohash.org/explicaboipsaimpedit.png?size=50x50&set=set1"},
{"id":12,"first_name":"Mellisent","last_name":"Rennox","email":"mrennoxb@wikispaces.com","saldo":8049037,"avatar":"https://robohash.org/estnisilaboriosam.png?size=50x50&set=set1"},
{"id":13,"first_name":"Ines","last_name":"Ibbison","email":"iibbisonc@is.gd","saldo":8156898,"avatar":"https://robohash.org/voluptatumeosperspiciatis.png?size=50x50&set=set1"},
{"id":14,"first_name":"Kerry","last_name":"Downie","email":"kdownied@berkeley.edu","saldo":3928767,"avatar":"https://robohash.org/temporanullapossimus.png?size=50x50&set=set1"},
{"id":15,"first_name":"Austina","last_name":"Benedetti","email":"abenedettie@rakuten.co.jp","saldo":7555123,"avatar":"https://robohash.org/ablaboriosamadipisci.png?size=50x50&set=set1"},
{"id":16,"first_name":"Gale","last_name":"Laugherane","email":"glaugheranef@cargocollective.com","saldo":4476996,"avatar":"https://robohash.org/laborumeumaut.png?size=50x50&set=set1"},
{"id":17,"first_name":"Kinny","last_name":"Gemmell","email":"kgemmellg@abc.net.au","saldo":4106933,"avatar":"https://robohash.org/ullamquodomnis.png?size=50x50&set=set1"},
{"id":18,"first_name":"Joyce","last_name":"Bothams","email":"jbothamsh@illinois.edu","saldo":1552573,"avatar":"https://robohash.org/autprovidentofficiis.png?size=50x50&set=set1"},
{"id":19,"first_name":"Uta","last_name":"Piolli","email":"upiollii@mediafire.com","saldo":3421985,"avatar":"https://robohash.org/laboreiurenecessitatibus.png?size=50x50&set=set1"},
{"id":20,"first_name":"Brit","last_name":"Vicarey","email":"bvicareyj@weather.com","saldo":6093431,"avatar":"https://robohash.org/dolorumomniseligendi.png?size=50x50&set=set1"},
{"id":21,"first_name":"Wilhelm","last_name":"Paolozzi","email":"wpaolozzik@vkontakte.ru","saldo":6459509,"avatar":"https://robohash.org/consequaturquamquis.png?size=50x50&set=set1"},
{"id":22,"first_name":"Hogan","last_name":"Pauletti","email":"hpaulettil@cbsnews.com","saldo":9906586,"avatar":"https://robohash.org/temporaquidoloremque.png?size=50x50&set=set1"},
{"id":23,"first_name":"Merrel","last_name":"McMeekan","email":"mmcmeekanm@yellowpages.com","saldo":9634343,"avatar":"https://robohash.org/quaeabdolorem.png?size=50x50&set=set1"},
{"id":24,"first_name":"Lanni","last_name":"Free","email":"lfreen@nba.com","saldo":6691189,"avatar":"https://robohash.org/eummolestiassit.png?size=50x50&set=set1"},
{"id":25,"first_name":"Zoe","last_name":"Caffery","email":"zcafferyo@usatoday.com","saldo":2135892,"avatar":"https://robohash.org/consequaturvoluptatibusvoluptates.png?size=50x50&set=set1"},
{"id":26,"first_name":"Brade","last_name":"Roloff","email":"broloffp@creativecommons.org","saldo":3595435,"avatar":"https://robohash.org/repudiandaealiasaut.png?size=50x50&set=set1"},
{"id":27,"first_name":"Robbi","last_name":"Jorat","email":"rjoratq@scribd.com","saldo":7443678,"avatar":"https://robohash.org/necessitatibusnonperferendis.png?size=50x50&set=set1"},
{"id":28,"first_name":"Lanita","last_name":"Hatcliffe","email":"lhatcliffer@blogspot.com","saldo":8768838,"avatar":"https://robohash.org/odioconsequunturvel.png?size=50x50&set=set1"},
{"id":29,"first_name":"Orly","last_name":"Matuska","email":"omatuskas@harvard.edu","saldo":9258344,"avatar":"https://robohash.org/namvelad.png?size=50x50&set=set1"},
{"id":30,"first_name":"Carolee","last_name":"Wiffler","email":"cwifflert@i2i.jp","saldo":710236,"avatar":"https://robohash.org/quonostrumomnis.png?size=50x50&set=set1"},
{"id":31,"first_name":"Julita","last_name":"Kolodziejski","email":"jkolodziejskiu@theguardian.com","saldo":4386768,"avatar":"https://robohash.org/voluptateaspernaturdoloribus.png?size=50x50&set=set1"},
{"id":32,"first_name":"Kalie","last_name":"Dixson","email":"kdixsonv@sitemeter.com","saldo":6018979,"avatar":"https://robohash.org/autcorporisminus.png?size=50x50&set=set1"},
{"id":33,"first_name":"Marline","last_name":"Tomczak","email":"mtomczakw@sohu.com","saldo":5207760,"avatar":"https://robohash.org/adoloresminima.png?size=50x50&set=set1"},
{"id":34,"first_name":"Reinaldo","last_name":"Roly","email":"rrolyx@jimdo.com","saldo":5296949,"avatar":"https://robohash.org/necessitatibusnonest.png?size=50x50&set=set1"},
{"id":35,"first_name":"Tish","last_name":"Unsworth","email":"tunsworthy@scientificamerican.com","saldo":9210908,"avatar":"https://robohash.org/culpacommodipraesentium.png?size=50x50&set=set1"},
{"id":36,"first_name":"Ursa","last_name":"Faulo","email":"ufauloz@whitehouse.gov","saldo":6932957,"avatar":"https://robohash.org/atqueeteum.png?size=50x50&set=set1"},
{"id":37,"first_name":"Garrard","last_name":"Creighton","email":"gcreighton10@facebook.com","saldo":6699004,"avatar":"https://robohash.org/estestdelectus.png?size=50x50&set=set1"},
{"id":38,"first_name":"Sallee","last_name":"Ivel","email":"sivel11@businessweek.com","saldo":817590,"avatar":"https://robohash.org/corruptisaepevoluptas.png?size=50x50&set=set1"},
{"id":39,"first_name":"Krishnah","last_name":"Willment","email":"kwillment12@netscape.com","saldo":5728684,"avatar":"https://robohash.org/sitanihil.png?size=50x50&set=set1"},
{"id":40,"first_name":"Lyn","last_name":"McMurraya","email":"lmcmurraya13@miibeian.gov.cn","saldo":3739610,"avatar":"https://robohash.org/atquiaperspiciatis.png?size=50x50&set=set1"},
{"id":41,"first_name":"Rebbecca","last_name":"Fenna","email":"rfenna14@omniture.com","saldo":6261339,"avatar":"https://robohash.org/nostrumiurererum.png?size=50x50&set=set1"},
{"id":42,"first_name":"Vaclav","last_name":"Masters","email":"vmasters15@histats.com","saldo":4439848,"avatar":"https://robohash.org/estrerumvoluptas.png?size=50x50&set=set1"},
{"id":43,"first_name":"Lanny","last_name":"Glasser","email":"lglasser16@webeden.co.uk","saldo":3434028,"avatar":"https://robohash.org/voluptatemiurenatus.png?size=50x50&set=set1"},
{"id":44,"first_name":"Otha","last_name":"Coffelt","email":"ocoffelt17@ucoz.com","saldo":8055928,"avatar":"https://robohash.org/modivoluptatemad.png?size=50x50&set=set1"},
{"id":45,"first_name":"Tadeas","last_name":"Kenningley","email":"tkenningley18@goo.gl","saldo":303303,"avatar":"https://robohash.org/quoipsamquo.png?size=50x50&set=set1"},
{"id":46,"first_name":"Hally","last_name":"Petheridge","email":"hpetheridge19@biblegateway.com","saldo":7226824,"avatar":"https://robohash.org/maximeeosillum.png?size=50x50&set=set1"},
{"id":47,"first_name":"Justinn","last_name":"Loghan","email":"jloghan1a@cocolog-nifty.com","saldo":7351771,"avatar":"https://robohash.org/autverofugiat.png?size=50x50&set=set1"},
{"id":48,"first_name":"Eadith","last_name":"Lead","email":"elead1b@nsw.gov.au","saldo":5125752,"avatar":"https://robohash.org/quiharumperferendis.png?size=50x50&set=set1"},
{"id":49,"first_name":"Casey","last_name":"Rosbotham","email":"crosbotham1c@senate.gov","saldo":9424388,"avatar":"https://robohash.org/architectoconsectetursequi.png?size=50x50&set=set1"},
{"id":50,"first_name":"Yehudit","last_name":"De Filippis","email":"ydefilippis1d@newyorker.com","saldo":4158033,"avatar":"https://robohash.org/recusandaemolestiaevoluptatibus.png?size=50x50&set=set1"},
{"id":51,"first_name":"Berne","last_name":"Karolyi","email":"bkarolyi1e@oracle.com","saldo":2132591,"avatar":"https://robohash.org/autquivoluptatem.png?size=50x50&set=set1"},
{"id":52,"first_name":"Temple","last_name":"Rallinshaw","email":"trallinshaw1f@gov.uk","saldo":9320345,"avatar":"https://robohash.org/doloraliquidfugiat.png?size=50x50&set=set1"},
{"id":53,"first_name":"Jana","last_name":"Kingscote","email":"jkingscote1g@istockphoto.com","saldo":3312472,"avatar":"https://robohash.org/quislaboriosamdolorum.png?size=50x50&set=set1"},
{"id":54,"first_name":"Hunter","last_name":"Radage","email":"hradage1h@creativecommons.org","saldo":1686587,"avatar":"https://robohash.org/sintnequeharum.png?size=50x50&set=set1"},
{"id":55,"first_name":"Dredi","last_name":"Horning","email":"dhorning1i@parallels.com","saldo":4404745,"avatar":"https://robohash.org/corruptivoluptatesrerum.png?size=50x50&set=set1"},
{"id":56,"first_name":"Heath","last_name":"Brussell","email":"hbrussell1j@pcworld.com","saldo":8819955,"avatar":"https://robohash.org/exercitationemeumquam.png?size=50x50&set=set1"},
{"id":57,"first_name":"Alfie","last_name":"Renon","email":"arenon1k@google.com.au","saldo":9893282,"avatar":"https://robohash.org/suntatquequae.png?size=50x50&set=set1"},
{"id":58,"first_name":"Brock","last_name":"Huntingford","email":"bhuntingford1l@virginia.edu","saldo":1930803,"avatar":"https://robohash.org/quinumquamblanditiis.png?size=50x50&set=set1"},
{"id":59,"first_name":"Nicolea","last_name":"Burrow","email":"nburrow1m@devhub.com","saldo":9003863,"avatar":"https://robohash.org/rerumexautem.png?size=50x50&set=set1"},
{"id":60,"first_name":"Jordana","last_name":"Jiranek","email":"jjiranek1n@stanford.edu","saldo":6531966,"avatar":"https://robohash.org/remnullasit.png?size=50x50&set=set1"},
{"id":61,"first_name":"Sadella","last_name":"Credland","email":"scredland1o@people.com.cn","saldo":982215,"avatar":"https://robohash.org/odioquistemporibus.png?size=50x50&set=set1"},
{"id":62,"first_name":"Shurlock","last_name":"Wickson","email":"swickson1p@cisco.com","saldo":4816816,"avatar":"https://robohash.org/aperiamquoid.png?size=50x50&set=set1"},
{"id":63,"first_name":"Frannie","last_name":"Newby","email":"fnewby1q@apple.com","saldo":7563373,"avatar":"https://robohash.org/atquedoloremquererum.png?size=50x50&set=set1"},
{"id":64,"first_name":"Hillie","last_name":"Gorry","email":"hgorry1r@globo.com","saldo":8474721,"avatar":"https://robohash.org/nisiperspiciatisaccusamus.png?size=50x50&set=set1"},
{"id":65,"first_name":"Lorri","last_name":"Doubrava","email":"ldoubrava1s@multiply.com","saldo":7247932,"avatar":"https://robohash.org/nemosuntnisi.png?size=50x50&set=set1"},
{"id":66,"first_name":"Colver","last_name":"Valentine","email":"cvalentine1t@bandcamp.com","saldo":4028908,"avatar":"https://robohash.org/nihilinet.png?size=50x50&set=set1"},
{"id":67,"first_name":"Richmond","last_name":"Upston","email":"rupston1u@ca.gov","saldo":9042240,"avatar":"https://robohash.org/maximeidaut.png?size=50x50&set=set1"},
{"id":68,"first_name":"Garek","last_name":"Dugue","email":"gdugue1v@engadget.com","saldo":6317830,"avatar":"https://robohash.org/istequisnihil.png?size=50x50&set=set1"},
{"id":69,"first_name":"Burgess","last_name":"Balmadier","email":"bbalmadier1w@ibm.com","saldo":3191192,"avatar":"https://robohash.org/sequievenietcorporis.png?size=50x50&set=set1"},
{"id":70,"first_name":"Ted","last_name":"Crosgrove","email":"tcrosgrove1x@sogou.com","saldo":3123696,"avatar":"https://robohash.org/quiaetdolor.png?size=50x50&set=set1"},
{"id":71,"first_name":"Bat","last_name":"Greguoli","email":"bgreguoli1y@nature.com","saldo":711712,"avatar":"https://robohash.org/recusandaevoluptasiste.png?size=50x50&set=set1"},
{"id":72,"first_name":"Garik","last_name":"Senescall","email":"gsenescall1z@vk.com","saldo":4896521,"avatar":"https://robohash.org/ipsumquicorporis.png?size=50x50&set=set1"},
{"id":73,"first_name":"Kata","last_name":"Curley","email":"kcurley20@yahoo.com","saldo":6938530,"avatar":"https://robohash.org/veroadipisciplaceat.png?size=50x50&set=set1"},
{"id":74,"first_name":"Konstantine","last_name":"Lighton","email":"klighton21@baidu.com","saldo":5079340,"avatar":"https://robohash.org/ipsaducimusminus.png?size=50x50&set=set1"},
{"id":75,"first_name":"Robbie","last_name":"Yerrall","email":"ryerrall22@elpais.com","saldo":8179553,"avatar":"https://robohash.org/voluptasnequeenim.png?size=50x50&set=set1"},
{"id":76,"first_name":"Filia","last_name":"Menendez","email":"fmenendez23@vkontakte.ru","saldo":3055336,"avatar":"https://robohash.org/autperferendiseos.png?size=50x50&set=set1"},
{"id":77,"first_name":"Jannel","last_name":"Tamas","email":"jtamas24@squidoo.com","saldo":6334170,"avatar":"https://robohash.org/estetex.png?size=50x50&set=set1"},
{"id":78,"first_name":"Gordie","last_name":"Fiske","email":"gfiske25@histats.com","saldo":8107418,"avatar":"https://robohash.org/etipsaomnis.png?size=50x50&set=set1"},
{"id":79,"first_name":"Rod","last_name":"Moulder","email":"rmoulder26@wordpress.com","saldo":6566395,"avatar":"https://robohash.org/liberoetmaxime.png?size=50x50&set=set1"},
{"id":80,"first_name":"Carmina","last_name":"Huertas","email":"chuertas27@dion.ne.jp","saldo":5144216,"avatar":"https://robohash.org/voluptatemquibusdambeatae.png?size=50x50&set=set1"},
{"id":81,"first_name":"Graehme","last_name":"Sandom","email":"gsandom28@alibaba.com","saldo":265490,"avatar":"https://robohash.org/eaauteos.png?size=50x50&set=set1"},
{"id":82,"first_name":"Briny","last_name":"Shutle","email":"bshutle29@shareasale.com","saldo":1325296,"avatar":"https://robohash.org/quitemporibusquod.png?size=50x50&set=set1"},
{"id":83,"first_name":"Adrian","last_name":"Geratt","email":"ageratt2a@patch.com","saldo":9815356,"avatar":"https://robohash.org/temporibusnihilerror.png?size=50x50&set=set1"},
{"id":84,"first_name":"Agnese","last_name":"Duckworth","email":"aduckworth2b@youku.com","saldo":9664370,"avatar":"https://robohash.org/etofficiaut.png?size=50x50&set=set1"},
{"id":85,"first_name":"Netty","last_name":"Bonsul","email":"nbonsul2c@ehow.com","saldo":6296522,"avatar":"https://robohash.org/fugiatquiadolor.png?size=50x50&set=set1"},
{"id":86,"first_name":"Doll","last_name":"Heeran","email":"dheeran2d@shinystat.com","saldo":1269992,"avatar":"https://robohash.org/autdictaqui.png?size=50x50&set=set1"},
{"id":87,"first_name":"Courtnay","last_name":"Ferguson","email":"cferguson2e@imageshack.us","saldo":2960101,"avatar":"https://robohash.org/blanditiistemporacum.png?size=50x50&set=set1"},
{"id":88,"first_name":"Emmit","last_name":"Blaise","email":"eblaise2f@comsenz.com","saldo":664558,"avatar":"https://robohash.org/quiaadipiscia.png?size=50x50&set=set1"},
{"id":89,"first_name":"Conny","last_name":"Haworth","email":"chaworth2g@pen.io","saldo":778213,"avatar":"https://robohash.org/asperioresnatuslaboriosam.png?size=50x50&set=set1"},
{"id":90,"first_name":"Adolpho","last_name":"Sherington","email":"asherington2h@nydailynews.com","saldo":5365566,"avatar":"https://robohash.org/blanditiisillumrerum.png?size=50x50&set=set1"},
{"id":91,"first_name":"Emmeline","last_name":"Skipper","email":"eskipper2i@psu.edu","saldo":5064554,"avatar":"https://robohash.org/doloremsitquo.png?size=50x50&set=set1"},
{"id":92,"first_name":"Donica","last_name":"Hamp","email":"dhamp2j@topsy.com","saldo":5381776,"avatar":"https://robohash.org/cumqueeumcorrupti.png?size=50x50&set=set1"},
{"id":93,"first_name":"Ibby","last_name":"Rattrie","email":"irattrie2k@rakuten.co.jp","saldo":1236478,"avatar":"https://robohash.org/nonquasiet.png?size=50x50&set=set1"},
{"id":94,"first_name":"Georgeanna","last_name":"Piser","email":"gpiser2l@exblog.jp","saldo":5746342,"avatar":"https://robohash.org/veniamautab.png?size=50x50&set=set1"},
{"id":95,"first_name":"Carey","last_name":"McComiskey","email":"cmccomiskey2m@is.gd","saldo":8472422,"avatar":"https://robohash.org/placeatadeleniti.png?size=50x50&set=set1"},
{"id":96,"first_name":"Dael","last_name":"Fallon","email":"dfallon2n@toplist.cz","saldo":5811104,"avatar":"https://robohash.org/essedolorexcepturi.png?size=50x50&set=set1"},
{"id":97,"first_name":"Pascale","last_name":"Wyld","email":"pwyld2o@nasa.gov","saldo":5873560,"avatar":"https://robohash.org/harumetdignissimos.png?size=50x50&set=set1"},
{"id":98,"first_name":"Legra","last_name":"Ducarne","email":"lducarne2p@cbslocal.com","saldo":4612728,"avatar":"https://robohash.org/aliquidautullam.png?size=50x50&set=set1"},
{"id":99,"first_name":"Laurena","last_name":"Berrecloth","email":"lberrecloth2q@shinystat.com","saldo":9139121,"avatar":"https://robohash.org/eumvoluptasdoloribus.png?size=50x50&set=set1"},
{"id":100,"first_name":"Twila","last_name":"Cornil","email":"tcornil2r@posterous.com","saldo":4689029,"avatar":"https://robohash.org/asedlaudantium.png?size=50x50&set=set1"}]